py360convert/__init__.py
py360convert/__main__.py
py360convert/c2e.py
py360convert/e2c.py
py360convert/e2p.py
py360convert/py.typed
py360convert/utils.py
py360convert-1.0.4.dist-info/LICENSE
py360convert-1.0.4.dist-info/METADATA
py360convert-1.0.4.dist-info/WHEEL
py360convert-1.0.4.dist-info/entry_points.txt
py360convert-1.0.4.dist-info/RECORD
