Metadata-Version: 2.1
Name: py360convert
Version: 1.0.4
Summary: Convertion between cubemap and equirectangular and also to perspective planar.
Home-page: https://github.com/sunset1995/py360convert
License: MIT
Author: Cheng Sun
Requires-Python: >=3.9,<4.0
Classifier: License :: OSI Approved :: MIT License
Classifier: Programming Language :: Python :: 3
Classifier: Programming Language :: Python :: 3.9
Classifier: Programming Language :: Python :: 3.10
Classifier: Programming Language :: Python :: 3.11
Classifier: Programming Language :: Python :: 3.12
Classifier: Programming Language :: Python :: 3.13
Requires-Dist: numpy (>=1.20.0) ; python_version < "3.13"
Requires-Dist: numpy (>=2.1.0) ; python_version >= "3.13"
Requires-Dist: pillow (>=6.0.0)
Requires-Dist: scipy (>=1.14.0) ; python_version >= "3.13"
Requires-Dist: scipy (>=1.2.0) ; python_version < "3.13"
Project-URL: Repository, https://github.com/sunset1995/py360convert
